hooks/__init__.py
hooks/executor.py
hooks/registry.py
multi_project_manager-0.0.11.dist-info/licenses/LICENSE
operations/__init__.py
operations/registry.py
plugins/patch_override.py
plugins/project_builder.py
plugins/project_manager.py
multi_project_manager-0.0.11.dist-info/METADATA
multi_project_manager-0.0.11.dist-info/WHEEL
multi_project_manager-0.0.11.dist-info/top_level.txt
multi_project_manager-0.0.11.dist-info/RECORD
