Metadata-Version: 2.4
Name: multi-project-manager
Version: 0.0.11
Summary: A comprehensive project and patch management tool for multi-board, multi-project environments with Git integration and automated PO (Patch/Override) operations.
Author-email: wangguanran <elvans.wang@gmail.com>
License-Expression: GPL-3.0
Project-URL: Homepage, https://github.com/wangguanran/ProjectManager
Project-URL: Bug Tracker, https://github.com/wangguanran/ProjectManager/issues
Project-URL: Repository, https://github.com/wangguanran/ProjectManager
Classifier: Development Status :: 4 - Beta
Classifier: Intended Audience :: Developers
Classifier: Intended Audience :: System Administrators
Classifier: Operating System :: OS Independent
Classifier: Programming Language :: Python :: 3
Classifier: Programming Language :: Python :: 3 :: Only
Classifier: Programming Language :: Python :: 3.8
Classifier: Programming Language :: Python :: 3.9
Classifier: Programming Language :: Python :: 3.10
Classifier: Programming Language :: Python :: 3.11
Classifier: Programming Language :: Python :: 3.12
Classifier: Topic :: Software Development :: Build Tools
Classifier: Topic :: Software Development :: Libraries :: Python Modules
Classifier: Topic :: Software Development :: Version Control :: Git
Classifier: Topic :: System :: Systems Administration
Classifier: Topic :: Utilities
Requires-Python: >=3.8
License-File: LICENSE
Requires-Dist: configupdater>=3.0.0
Requires-Dist: toml>=0.10.2
Requires-Dist: GitPython>=3.1.40
Requires-Dist: importlib-metadata; python_version < "3.8"
Provides-Extra: dev
Requires-Dist: build>=1.0.0; extra == "dev"
Requires-Dist: pytest>=7.4.0; extra == "dev"
Requires-Dist: pytest-cov>=4.1.0; extra == "dev"
Requires-Dist: pyinstaller>=6.0.0; extra == "dev"
Requires-Dist: pylint>=3.0.0; extra == "dev"
Requires-Dist: black>=23.0.0; extra == "dev"
Requires-Dist: isort>=5.12.0; extra == "dev"
Requires-Dist: mypy>=1.5.0; extra == "dev"
Requires-Dist: pre-commit>=3.3.0; extra == "dev"
Dynamic: license-file
